phply-1.2.6-py3.10-nspkg.pth
phply/parsetab.py
phply/phpast.py
phply/phplex.py
phply/phpparse.py
phply/pythonast.py
tests/__init__.py
tests/test_filtered_lexer.py
tests/test_lexer.py
tests/test_parser.py
phply-1.2.6.dist-info/AUTHORS
phply-1.2.6.dist-info/LICENSE
phply-1.2.6.dist-info/METADATA
phply-1.2.6.dist-info/WHEEL
phply-1.2.6.dist-info/entry_points.txt
phply-1.2.6.dist-info/namespace_packages.txt
phply-1.2.6.dist-info/top_level.txt
phply-1.2.6.dist-info/RECORD
